vl_convert/__init__.py
vl_convert/__init__.pyi
vl_convert/py.typed
vl_convert/vl_convert.pyd
vl_convert_python-1.9.0.dist-info/METADATA
vl_convert_python-1.9.0.dist-info/WHEEL
vl_convert_python-1.9.0.dist-info/licenses/LICENSE
vl_convert_python-1.9.0.dist-info/RECORD
