Metadata-Version: 2.4
Name: vl-convert-python
Version: 1.9.0
Classifier: Programming Language :: Rust
Classifier: Programming Language :: Python :: Implementation :: CPython
License-File: LICENSE
Summary: Convert Vega-Lite chart specifications to SVG, PNG, or Vega
Home-Page: https://github.com/jonmmease/vl-convert
Requires-Python: >=3.7
